{
  "Type": "BalefireBlast",
  "NumExplosions": 10,
  "ExplosionSeparation": 2,
  "ExplosionParticles": {
    "SystemId": "Explosion_Medium"
  },
  "ExplosionConfig": {
    "DamageEntities": true,
    "DamageBlocks": true,
    "BlockDamageRadius": 2,
    "BlockDropChance": 0,
    "EntityDamage": 75,
    "EntityDamageRadius": 5,
    "Knockback": {
      "Type": "Point",
      "VelocityConfig": {
        "AirResistance": 0.97,
        "AirResistanceMax": 0.96,
        "Direction": {
          "X": 0.0,
          "Y": 5.0,
          "Z": 0.0
        },
        "GroundResistance": 0.94,
        "GroundResistanceMax": 0.3,
        "Threshold": 3.0
      },
      "Force": 5,
      "VelocityType": "Set"
    },
    "ItemTool": {
      "Specs": [
        {
          "Power": 2,
          "GatherType": "SoftBlocks"
        },
        {
          "Power": 2,
          "GatherType": "Soils"
        },
        {
          "Power": 2,
          "GatherType": "Woods"
        },
        {
          "Power": 2,
          "GatherType": "Rocks"
        },
        {
          "Power": 2,
          "GatherType": "Benches"
        },
        {
          "Power": 1,
          "GatherType": "VolcanicRocks"
        }
      ]
    }
  },
  "RunTime": 0,
  "ExplosionSoundId": "SFX_Goblin_Lobber_Bomb_Death"
}
